morsecode_enhanced/__init__.py
morsecode_enhanced/morsecode_enhanced.py
morsecode_enhanced-1.0.1.dist-info/LICENSE.txt
morsecode_enhanced-1.0.1.dist-info/METADATA
morsecode_enhanced-1.0.1.dist-info/WHEEL
morsecode_enhanced-1.0.1.dist-info/top_level.txt
morsecode_enhanced-1.0.1.dist-info/RECORD
