Metadata-Version: 2.1
Name: morsecode-enhanced
Version: 1.0.1
Summary: A package for encoding and decoding Morse code.
Home-page: https://github.com/danysrour/morsecode_enhanced
Author: Dany Srour
Author-email: dany.srour@gmail.com
Classifier: Development Status :: 5 - Production/Stable
Classifier: Intended Audience :: Developers
Classifier: License :: OSI Approved :: MIT License
Classifier: Programming Language :: Python :: 3
Classifier: Programming Language :: Python :: 3.6
Classifier: Programming Language :: Python :: 3.7
Classifier: Programming Language :: Python :: 3.8
Classifier: Programming Language :: Python :: 3.9
Requires-Python: >=3.6
License-File: LICENSE.txt
